nonebot_plugin_biliav/__init__.py
nonebot_plugin_biliav/data_source.py
nonebot_plugin_biliav-1.0.12.dist-info/METADATA
nonebot_plugin_biliav-1.0.12.dist-info/WHEEL
nonebot_plugin_biliav-1.0.12.dist-info/RECORD
