Metadata-Version: 2.1
Name: nonebot_plugin_biliav
Version: 1.0.12
Summary: NoneBot biliav小程序 查看插件
License: MIT
Author: knva
Author-email: txt_ch@163.com
Requires-Python: >=3.9.0,<4.0.0
Classifier: License :: OSI Approved :: MIT License
Classifier: Programming Language :: Python :: 3
Classifier: Programming Language :: Python :: 3.9
Classifier: Programming Language :: Python :: 3.10
Classifier: Programming Language :: Python :: 3.11
Classifier: Programming Language :: Python :: 3.12
Requires-Dist: httpx (>=0.18.0,<1.0.0)
Requires-Dist: nonebot-adapter-onebot (>=2.0.0-beta.1,<3.0.0)
Requires-Dist: nonebot2 (>=2.0.0-beta.1,<3.0.0)
